LICENSE
README.md
setup.py
school_mosreg_api/__init__.py
school_mosreg_api/exceptions.py
school_mosreg_api/py.typed
school_mosreg_api.egg-info/PKG-INFO
school_mosreg_api.egg-info/SOURCES.txt
school_mosreg_api.egg-info/dependency_links.txt
school_mosreg_api.egg-info/top_level.txt
school_mosreg_api/api/__init__.py
school_mosreg_api/api/base.py
school_mosreg_api/api/methods.py
school_mosreg_api/asyncapi/__init__.py
school_mosreg_api/asyncapi/base.py
school_mosreg_api/asyncapi/methods.py
school_mosreg_api/types/Authorities.py
school_mosreg_api/types/Authorizations.py
school_mosreg_api/types/Children.py
school_mosreg_api/types/Context.py
school_mosreg_api/types/EduGroups.py
school_mosreg_api/types/EducationMemberships.py
school_mosreg_api/types/FinalMarks.py
school_mosreg_api/types/Homeworks.py
school_mosreg_api/types/LessonLog.py
school_mosreg_api/types/Lessons.py
school_mosreg_api/types/MarkHistograms.py
school_mosreg_api/types/Marks.py
school_mosreg_api/types/Persons.py
school_mosreg_api/types/RecentMarks.py
school_mosreg_api/types/ReportingPeriods.py
school_mosreg_api/types/Schedules.py
school_mosreg_api/types/Schools.py
school_mosreg_api/types/SchoolsParameters.py
school_mosreg_api/types/Subjects.py
school_mosreg_api/types/Tasks.py
school_mosreg_api/types/Teacher.py
school_mosreg_api/types/Timetables.py
school_mosreg_api/types/UserFeeds.py
school_mosreg_api/types/UserRelatives.py
school_mosreg_api/types/Users.py
school_mosreg_api/types/WeightedAverageMarks.py
school_mosreg_api/types/WorkTypes.py
school_mosreg_api/types/Works.py
school_mosreg_api/types/__init__.py
school_mosreg_api/types/model.py